{
  "model_type": "ThetaSketchDecisionTree",
  "lg_k": 18,
  "hyperparameters": {
    "criterion": "gini",
    "max_depth": 6,
    "min_samples_split": 100,
    "min_samples_leaf": 50
  },
  "tree_structure": {
    "depth": 0,
    "n_samples": 20343.0,
    "ancestry": "root",
    "class_counts": [
      17735.0,
      2608.0
    ],
    "impurity": 0.2235,
    "is_leaf": false,
    "type": "split",
    "feature_name": "pickUpHourOfDay=VERYLATE",
    "feature_idx": 33,
    "split_condition": "pickUpHourOfDay=VERYLATE == 1",
    "left_condition": "pickUpHourOfDay=VERYLATE == 0 (FALSE/NOT)",
    "right_condition": "pickUpHourOfDay=VERYLATE == 1 (TRUE)",
    "left": {
      "depth": 1,
      "n_samples": 18013.0,
      "ancestry": "pickUpHourOfDay=VERYLATE!=1",
      "class_counts": [
        15927.0,
        2086.0
      ],
      "impurity": 0.2048,
      "is_leaf": false,
      "type": "split",
      "feature_name": "zone_demand_popularity=POPULARITY_INDEX_5",
      "feature_idx": 353,
      "split_condition": "zone_demand_popularity=POPULARITY_INDEX_5 == 1",
      "left_condition": "zone_demand_popularity=POPULARITY_INDEX_5 == 0 (FALSE/NOT)",
      "right_condition": "zone_demand_popularity=POPULARITY_INDEX_5 == 1 (TRUE)",
      "left": {
        "depth": 2,
        "n_samples": 15446.0,
        "ancestry": "pickUpHourOfDay=VERYLATE!=1 and zone_demand_popularity=POPULARITY_INDEX_5!=1",
        "class_counts": [
          13829.0,
          1617.0
        ],
        "impurity": 0.1875,
        "is_leaf": false,
        "type": "split",
        "feature_name": "pickUpHourOfDay=LATENIGHT",
        "feature_idx": 30,
        "split_condition": "pickUpHourOfDay=LATENIGHT == 1",
        "left_condition": "pickUpHourOfDay=LATENIGHT == 0 (FALSE/NOT)",
        "right_condition": "pickUpHourOfDay=LATENIGHT == 1 (TRUE)",
        "left": {
          "depth": 3,
          "n_samples": 13808.0,
          "ancestry": "pickUpHourOfDay=VERYLATE!=1 and zone_demand_popularity=POPULARITY_INDEX_5!=1 and pickUpHourOfDay=LATENIGHT!=1",
          "class_counts": [
            12476.0,
            1332.0
          ],
          "impurity": 0.1743,
          "is_leaf": false,
          "type": "split",
          "feature_name": "zone=221",
          "feature_idx": 92,
          "split_condition": "zone=221 == 1",
          "left_condition": "zone=221 == 0 (FALSE/NOT)",
          "right_condition": "zone=221 == 1 (TRUE)",
          "left": {
            "depth": 4,
            "n_samples": 13560.0,
            "ancestry": "pickUpHourOfDay=VERYLATE!=1 and zone_demand_popularity=POPULARITY_INDEX_5!=1 and pickUpHourOfDay=LATENIGHT!=1 and zone=221!=1",
            "class_counts": [
              12292.0,
              1268.0
            ],
            "impurity": 0.1695,
            "is_leaf": false,
            "type": "split",
            "feature_name": "zone=194",
            "feature_idx": 78,
            "split_condition": "zone=194 == 1",
            "left_condition": "zone=194 == 0 (FALSE/NOT)",
            "right_condition": "zone=194 == 1 (TRUE)",
            "left": {
              "depth": 5,
              "n_samples": 13491.0,
              "ancestry": "pickUpHourOfDay=VERYLATE!=1 and zone_demand_popularity=POPULARITY_INDEX_5!=1 and pickUpHourOfDay=LATENIGHT!=1 and zone=221!=1 and zone=194!=1",
              "class_counts": [
                12250.0,
                1241.0
              ],
              "impurity": 0.1671,
              "is_leaf": false,
              "type": "split",
              "feature_name": "sla=Immediate",
              "feature_idx": 34,
              "split_condition": "sla=Immediate == 1",
              "left_condition": "sla=Immediate == 0 (FALSE/NOT)",
              "right_condition": "sla=Immediate == 1 (TRUE)",
              "left": {
                "depth": 6,
                "n_samples": 12794.0,
                "ancestry": "pickUpHourOfDay=VERYLATE!=1 and zone_demand_popularity=POPULARITY_INDEX_5!=1 and pickUpHourOfDay=LATENIGHT!=1 and zone=221!=1 and zone=194!=1 and sla=Immediate!=1",
                "class_counts": [
                  11560.0,
                  1234.0
                ],
                "impurity": 0.1743,
                "is_leaf": true,
                "type": "leaf",
                "prediction": 0,
                "probabilities": [
                  0.9035,
                  0.0965
                ]
              },
              "right": {
                "depth": 6,
                "n_samples": 697.0,
                "ancestry": "pickUpHourOfDay=VERYLATE!=1 and zone_demand_popularity=POPULARITY_INDEX_5!=1 and pickUpHourOfDay=LATENIGHT!=1 and zone=221!=1 and zone=194!=1 and sla=Immediate==1",
                "class_counts": [
                  690.0,
                  7.0
                ],
                "impurity": 0.0199,
                "is_leaf": true,
                "type": "leaf",
                "prediction": 0,
                "probabilities": [
                  0.99,
                  0.01
                ]
              }
            },
            "right": {
              "depth": 5,
              "n_samples": 69.0,
              "ancestry": "pickUpHourOfDay=VERYLATE!=1 and zone_demand_popularity=POPULARITY_INDEX_5!=1 and pickUpHourOfDay=LATENIGHT!=1 and zone=221!=1 and zone=194==1",
              "class_counts": [
                42.0,
                27.0
              ],
              "impurity": 0.4764,
              "is_leaf": true,
              "type": "leaf",
              "prediction": 0,
              "probabilities": [
                0.6087,
                0.3913
              ]
            }
          },
          "right": {
            "depth": 4,
            "n_samples": 248.0,
            "ancestry": "pickUpHourOfDay=VERYLATE!=1 and zone_demand_popularity=POPULARITY_INDEX_5!=1 and pickUpHourOfDay=LATENIGHT!=1 and zone=221==1",
            "class_counts": [
              184.0,
              64.0
            ],
            "impurity": 0.3829,
            "is_leaf": false,
            "type": "split",
            "feature_name": "booking_type=one_way_trip",
            "feature_idx": 7,
            "split_condition": "booking_type=one_way_trip == 1",
            "left_condition": "booking_type=one_way_trip == 0 (FALSE/NOT)",
            "right_condition": "booking_type=one_way_trip == 1 (TRUE)",
            "left": {
              "depth": 5,
              "n_samples": 158.0,
              "ancestry": "pickUpHourOfDay=VERYLATE!=1 and zone_demand_popularity=POPULARITY_INDEX_5!=1 and pickUpHourOfDay=LATENIGHT!=1 and zone=221==1 and booking_type=one_way_trip!=1",
              "class_counts": [
                129.0,
                29.0
              ],
              "impurity": 0.2997,
              "is_leaf": false,
              "type": "split",
              "feature_name": "estimated_usage_bins=GT_3_LTE_4_HOURS",
              "feature_idx": 21,
              "split_condition": "estimated_usage_bins=GT_3_LTE_4_HOURS == 1",
              "left_condition": "estimated_usage_bins=GT_3_LTE_4_HOURS == 0 (FALSE/NOT)",
              "right_condition": "estimated_usage_bins=GT_3_LTE_4_HOURS == 1 (TRUE)",
              "left": {
                "depth": 6,
                "n_samples": 97.0,
                "ancestry": "pickUpHourOfDay=VERYLATE!=1 and zone_demand_popularity=POPULARITY_INDEX_5!=1 and pickUpHourOfDay=LATENIGHT!=1 and zone=221==1 and booking_type=one_way_trip!=1 and estimated_usage_bins=GT_3_LTE_4_HOURS!=1",
                "class_counts": [
                  82.0,
                  15.0
                ],
                "impurity": 0.2615,
                "is_leaf": true,
                "type": "leaf",
                "prediction": 0,
                "probabilities": [
                  0.8454,
                  0.1546
                ]
              },
              "right": {
                "depth": 6,
                "n_samples": 61.0,
                "ancestry": "pickUpHourOfDay=VERYLATE!=1 and zone_demand_popularity=POPULARITY_INDEX_5!=1 and pickUpHourOfDay=LATENIGHT!=1 and zone=221==1 and booking_type=one_way_trip!=1 and estimated_usage_bins=GT_3_LTE_4_HOURS==1",
                "class_counts": [
                  47.0,
                  14.0
                ],
                "impurity": 0.3537,
                "is_leaf": true,
                "type": "leaf",
                "prediction": 0,
                "probabilities": [
                  0.7705,
                  0.2295
                ]
              }
            },
            "right": {
              "depth": 5,
              "n_samples": 90.0,
              "ancestry": "pickUpHourOfDay=VERYLATE!=1 and zone_demand_popularity=POPULARITY_INDEX_5!=1 and pickUpHourOfDay=LATENIGHT!=1 and zone=221==1 and booking_type=one_way_trip==1",
              "class_counts": [
                55.0,
                35.0
              ],
              "impurity": 0.4753,
              "is_leaf": true,
              "type": "leaf",
              "prediction": 0,
              "probabilities": [
                0.6111,
                0.3889
              ]
            }
          }
        },
        "right": {
          "depth": 3,
          "n_samples": 1638.0,
          "ancestry": "pickUpHourOfDay=VERYLATE!=1 and zone_demand_popularity=POPULARITY_INDEX_5!=1 and pickUpHourOfDay=LATENIGHT==1",
          "class_counts": [
            1353.0,
            285.0
          ],
          "impurity": 0.2874,
          "is_leaf": false,
          "type": "split",
          "feature_name": "dayType=NORMAL_WEEKDAY",
          "feature_idx": 17,
          "split_condition": "dayType=NORMAL_WEEKDAY == 1",
          "left_condition": "dayType=NORMAL_WEEKDAY == 0 (FALSE/NOT)",
          "right_condition": "dayType=NORMAL_WEEKDAY == 1 (TRUE)",
          "left": {
            "depth": 4,
            "n_samples": 936.0,
            "ancestry": "pickUpHourOfDay=VERYLATE!=1 and zone_demand_popularity=POPULARITY_INDEX_5!=1 and pickUpHourOfDay=LATENIGHT==1 and dayType=NORMAL_WEEKDAY!=1",
            "class_counts": [
              717.0,
              219.0
            ],
            "impurity": 0.3585,
            "is_leaf": false,
            "type": "split",
            "feature_name": "zone=217",
            "feature_idx": 88,
            "split_condition": "zone=217 == 1",
            "left_condition": "zone=217 == 0 (FALSE/NOT)",
            "right_condition": "zone=217 == 1 (TRUE)",
            "left": {
              "depth": 5,
              "n_samples": 874.0,
              "ancestry": "pickUpHourOfDay=VERYLATE!=1 and zone_demand_popularity=POPULARITY_INDEX_5!=1 and pickUpHourOfDay=LATENIGHT==1 and dayType=NORMAL_WEEKDAY!=1 and zone=217!=1",
              "class_counts": [
                657.0,
                217.0
              ],
              "impurity": 0.3733,
              "is_leaf": false,
              "type": "split",
              "feature_name": "city=Mumbai",
              "feature_idx": 14,
              "split_condition": "city=Mumbai == 1",
              "left_condition": "city=Mumbai == 0 (FALSE/NOT)",
              "right_condition": "city=Mumbai == 1 (TRUE)",
              "left": {
                "depth": 6,
                "n_samples": 644.0,
                "ancestry": "pickUpHourOfDay=VERYLATE!=1 and zone_demand_popularity=POPULARITY_INDEX_5!=1 and pickUpHourOfDay=LATENIGHT==1 and dayType=NORMAL_WEEKDAY!=1 and zone=217!=1 and city=Mumbai!=1",
                "class_counts": [
                  464.0,
                  180.0
                ],
                "impurity": 0.4028,
                "is_leaf": true,
                "type": "leaf",
                "prediction": 0,
                "probabilities": [
                  0.7205,
                  0.2795
                ]
              },
              "right": {
                "depth": 6,
                "n_samples": 230.0,
                "ancestry": "pickUpHourOfDay=VERYLATE!=1 and zone_demand_popularity=POPULARITY_INDEX_5!=1 and pickUpHourOfDay=LATENIGHT==1 and dayType=NORMAL_WEEKDAY!=1 and zone=217!=1 and city=Mumbai==1",
                "class_counts": [
                  193.0,
                  37.0
                ],
                "impurity": 0.27,
                "is_leaf": true,
                "type": "leaf",
                "prediction": 0,
                "probabilities": [
                  0.8391,
                  0.1609
                ]
              }
            },
            "right": {
              "depth": 5,
              "n_samples": 62.0,
              "ancestry": "pickUpHourOfDay=VERYLATE!=1 and zone_demand_popularity=POPULARITY_INDEX_5!=1 and pickUpHourOfDay=LATENIGHT==1 and dayType=NORMAL_WEEKDAY!=1 and zone=217==1",
              "class_counts": [
                60.0,
                2.0
              ],
              "impurity": 0.0624,
              "is_leaf": true,
              "type": "leaf",
              "prediction": 0,
              "probabilities": [
                0.9677,
                0.0323
              ]
            }
          },
          "right": {
            "depth": 4,
            "n_samples": 702.0,
            "ancestry": "pickUpHourOfDay=VERYLATE!=1 and zone_demand_popularity=POPULARITY_INDEX_5!=1 and pickUpHourOfDay=LATENIGHT==1 and dayType=NORMAL_WEEKDAY==1",
            "class_counts": [
              636.0,
              66.0
            ],
            "impurity": 0.1704,
            "is_leaf": false,
            "type": "split",
            "feature_name": "zone_demand_popularity=POPULARITY_INDEX_1",
            "feature_idx": 349,
            "split_condition": "zone_demand_popularity=POPULARITY_INDEX_1 == 1",
            "left_condition": "zone_demand_popularity=POPULARITY_INDEX_1 == 0 (FALSE/NOT)",
            "right_condition": "zone_demand_popularity=POPULARITY_INDEX_1 == 1 (TRUE)",
            "left": {
              "depth": 5,
              "n_samples": 365.0,
              "ancestry": "pickUpHourOfDay=VERYLATE!=1 and zone_demand_popularity=POPULARITY_INDEX_5!=1 and pickUpHourOfDay=LATENIGHT==1 and dayType=NORMAL_WEEKDAY==1 and zone_demand_popularity=POPULARITY_INDEX_1!=1",
              "class_counts": [
                316.0,
                49.0
              ],
              "impurity": 0.2324,
              "is_leaf": false,
              "type": "split",
              "feature_name": "city=Mumbai",
              "feature_idx": 14,
              "split_condition": "city=Mumbai == 1",
              "left_condition": "city=Mumbai == 0 (FALSE/NOT)",
              "right_condition": "city=Mumbai == 1 (TRUE)",
              "left": {
                "depth": 6,
                "n_samples": 249.0,
                "ancestry": "pickUpHourOfDay=VERYLATE!=1 and zone_demand_popularity=POPULARITY_INDEX_5!=1 and pickUpHourOfDay=LATENIGHT==1 and dayType=NORMAL_WEEKDAY==1 and zone_demand_popularity=POPULARITY_INDEX_1!=1 and city=Mumbai!=1",
                "class_counts": [
                  204.0,
                  45.0
                ],
                "impurity": 0.2961,
                "is_leaf": true,
                "type": "leaf",
                "prediction": 0,
                "probabilities": [
                  0.8193,
                  0.1807
                ]
              },
              "right": {
                "depth": 6,
                "n_samples": 116.0,
                "ancestry": "pickUpHourOfDay=VERYLATE!=1 and zone_demand_popularity=POPULARITY_INDEX_5!=1 and pickUpHourOfDay=LATENIGHT==1 and dayType=NORMAL_WEEKDAY==1 and zone_demand_popularity=POPULARITY_INDEX_1!=1 and city=Mumbai==1",
                "class_counts": [
                  112.0,
                  4.0
                ],
                "impurity": 0.0666,
                "is_leaf": true,
                "type": "leaf",
                "prediction": 0,
                "probabilities": [
                  0.9655,
                  0.0345
                ]
              }
            },
            "right": {
              "depth": 5,
              "n_samples": 337.0,
              "ancestry": "pickUpHourOfDay=VERYLATE!=1 and zone_demand_popularity=POPULARITY_INDEX_5!=1 and pickUpHourOfDay=LATENIGHT==1 and dayType=NORMAL_WEEKDAY==1 and zone_demand_popularity=POPULARITY_INDEX_1==1",
              "class_counts": [
                320.0,
                17.0
              ],
              "impurity": 0.0958,
              "is_leaf": false,
              "type": "split",
              "feature_name": "zone=219",
              "feature_idx": 90,
              "split_condition": "zone=219 == 1",
              "left_condition": "zone=219 == 0 (FALSE/NOT)",
              "right_condition": "zone=219 == 1 (TRUE)",
              "left": {
                "depth": 6,
                "n_samples": 241.0,
                "ancestry": "pickUpHourOfDay=VERYLATE!=1 and zone_demand_popularity=POPULARITY_INDEX_5!=1 and pickUpHourOfDay=LATENIGHT==1 and dayType=NORMAL_WEEKDAY==1 and zone_demand_popularity=POPULARITY_INDEX_1==1 and zone=219!=1",
                "class_counts": [
                  227.0,
                  14.0
                ],
                "impurity": 0.1094,
                "is_leaf": true,
                "type": "leaf",
                "prediction": 0,
                "probabilities": [
                  0.9419,
                  0.0581
                ]
              },
              "right": {
                "depth": 6,
                "n_samples": 96.0,
                "ancestry": "pickUpHourOfDay=VERYLATE!=1 and zone_demand_popularity=POPULARITY_INDEX_5!=1 and pickUpHourOfDay=LATENIGHT==1 and dayType=NORMAL_WEEKDAY==1 and zone_demand_popularity=POPULARITY_INDEX_1==1 and zone=219==1",
                "class_counts": [
                  93.0,
                  3.0
                ],
                "impurity": 0.0605,
                "is_leaf": true,
                "type": "leaf",
                "prediction": 0,
                "probabilities": [
                  0.9688,
                  0.0312
                ]
              }
            }
          }
        }
      },
      "right": {
        "depth": 2,
        "n_samples": 2567.0,
        "ancestry": "pickUpHourOfDay=VERYLATE!=1 and zone_demand_popularity=POPULARITY_INDEX_5==1",
        "class_counts": [
          2098.0,
          469.0
        ],
        "impurity": 0.2986,
        "is_leaf": false,
        "type": "split",
        "feature_name": "pickUpHourOfDay=LATENIGHT",
        "feature_idx": 30,
        "split_condition": "pickUpHourOfDay=LATENIGHT == 1",
        "left_condition": "pickUpHourOfDay=LATENIGHT == 0 (FALSE/NOT)",
        "right_condition": "pickUpHourOfDay=LATENIGHT == 1 (TRUE)",
        "left": {
          "depth": 3,
          "n_samples": 2428.0,
          "ancestry": "pickUpHourOfDay=VERYLATE!=1 and zone_demand_popularity=POPULARITY_INDEX_5==1 and pickUpHourOfDay=LATENIGHT!=1",
          "class_counts": [
            2017.0,
            411.0
          ],
          "impurity": 0.2812,
          "is_leaf": false,
          "type": "split",
          "feature_name": "city=Pune",
          "feature_idx": 15,
          "split_condition": "city=Pune == 1",
          "left_condition": "city=Pune == 0 (FALSE/NOT)",
          "right_condition": "city=Pune == 1 (TRUE)",
          "left": {
            "depth": 4,
            "n_samples": 2075.0,
            "ancestry": "pickUpHourOfDay=VERYLATE!=1 and zone_demand_popularity=POPULARITY_INDEX_5==1 and pickUpHourOfDay=LATENIGHT!=1 and city=Pune!=1",
            "class_counts": [
              1765.0,
              310.0
            ],
            "impurity": 0.2542,
            "is_leaf": false,
            "type": "split",
            "feature_name": "city=Mumbai",
            "feature_idx": 14,
            "split_condition": "city=Mumbai == 1",
            "left_condition": "city=Mumbai == 0 (FALSE/NOT)",
            "right_condition": "city=Mumbai == 1 (TRUE)",
            "left": {
              "depth": 5,
              "n_samples": 1489.0,
              "ancestry": "pickUpHourOfDay=VERYLATE!=1 and zone_demand_popularity=POPULARITY_INDEX_5==1 and pickUpHourOfDay=LATENIGHT!=1 and city=Pune!=1 and city=Mumbai!=1",
              "class_counts": [
                1310.0,
                179.0
              ],
              "impurity": 0.2115,
              "is_leaf": false,
              "type": "split",
              "feature_name": "city=Hyderabad",
              "feature_idx": 13,
              "split_condition": "city=Hyderabad == 1",
              "left_condition": "city=Hyderabad == 0 (FALSE/NOT)",
              "right_condition": "city=Hyderabad == 1 (TRUE)",
              "left": {
                "depth": 6,
                "n_samples": 1397.0,
                "ancestry": "pickUpHourOfDay=VERYLATE!=1 and zone_demand_popularity=POPULARITY_INDEX_5==1 and pickUpHourOfDay=LATENIGHT!=1 and city=Pune!=1 and city=Mumbai!=1 and city=Hyderabad!=1",
                "class_counts": [
                  1244.0,
                  153.0
                ],
                "impurity": 0.1951,
                "is_leaf": true,
                "type": "leaf",
                "prediction": 0,
                "probabilities": [
                  0.8905,
                  0.1095
                ]
              },
              "right": {
                "depth": 6,
                "n_samples": 92.0,
                "ancestry": "pickUpHourOfDay=VERYLATE!=1 and zone_demand_popularity=POPULARITY_INDEX_5==1 and pickUpHourOfDay=LATENIGHT!=1 and city=Pune!=1 and city=Mumbai!=1 and city=Hyderabad==1",
                "class_counts": [
                  66.0,
                  26.0
                ],
                "impurity": 0.4055,
                "is_leaf": true,
                "type": "leaf",
                "prediction": 0,
                "probabilities": [
                  0.7174,
                  0.2826
                ]
              }
            },
            "right": {
              "depth": 5,
              "n_samples": 586.0,
              "ancestry": "pickUpHourOfDay=VERYLATE!=1 and zone_demand_popularity=POPULARITY_INDEX_5==1 and pickUpHourOfDay=LATENIGHT!=1 and city=Pune!=1 and city=Mumbai==1",
              "class_counts": [
                455.0,
                131.0
              ],
              "impurity": 0.3472,
              "is_leaf": false,
              "type": "split",
              "feature_name": "booking_type=round_trip",
              "feature_idx": 9,
              "split_condition": "booking_type=round_trip == 1",
              "left_condition": "booking_type=round_trip == 0 (FALSE/NOT)",
              "right_condition": "booking_type=round_trip == 1 (TRUE)",
              "left": {
                "depth": 6,
                "n_samples": 397.0,
                "ancestry": "pickUpHourOfDay=VERYLATE!=1 and zone_demand_popularity=POPULARITY_INDEX_5==1 and pickUpHourOfDay=LATENIGHT!=1 and city=Pune!=1 and city=Mumbai==1 and booking_type=round_trip!=1",
                "class_counts": [
                  326.0,
                  71.0
                ],
                "impurity": 0.2937,
                "is_leaf": true,
                "type": "leaf",
                "prediction": 0,
                "probabilities": [
                  0.8212,
                  0.1788
                ]
              },
              "right": {
                "depth": 6,
                "n_samples": 189.0,
                "ancestry": "pickUpHourOfDay=VERYLATE!=1 and zone_demand_popularity=POPULARITY_INDEX_5==1 and pickUpHourOfDay=LATENIGHT!=1 and city=Pune!=1 and city=Mumbai==1 and booking_type=round_trip==1",
                "class_counts": [
                  129.0,
                  60.0
                ],
                "impurity": 0.4334,
                "is_leaf": true,
                "type": "leaf",
                "prediction": 0,
                "probabilities": [
                  0.6825,
                  0.3175
                ]
              }
            }
          },
          "right": {
            "depth": 4,
            "n_samples": 353.0,
            "ancestry": "pickUpHourOfDay=VERYLATE!=1 and zone_demand_popularity=POPULARITY_INDEX_5==1 and pickUpHourOfDay=LATENIGHT!=1 and city=Pune==1",
            "class_counts": [
              252.0,
              101.0
            ],
            "impurity": 0.4085,
            "is_leaf": false,
            "type": "split",
            "feature_name": "booking_type=outstation",
            "feature_idx": 8,
            "split_condition": "booking_type=outstation == 1",
            "left_condition": "booking_type=outstation == 0 (FALSE/NOT)",
            "right_condition": "booking_type=outstation == 1 (TRUE)",
            "left": {
              "depth": 5,
              "n_samples": 291.0,
              "ancestry": "pickUpHourOfDay=VERYLATE!=1 and zone_demand_popularity=POPULARITY_INDEX_5==1 and pickUpHourOfDay=LATENIGHT!=1 and city=Pune==1 and booking_type=outstation!=1",
              "class_counts": [
                196.0,
                95.0
              ],
              "impurity": 0.4398,
              "is_leaf": false,
              "type": "split",
              "feature_name": "pickUpHourOfDay=MORNING",
              "feature_idx": 31,
              "split_condition": "pickUpHourOfDay=MORNING == 1",
              "left_condition": "pickUpHourOfDay=MORNING == 0 (FALSE/NOT)",
              "right_condition": "pickUpHourOfDay=MORNING == 1 (TRUE)",
              "left": {
                "depth": 6,
                "n_samples": 201.0,
                "ancestry": "pickUpHourOfDay=VERYLATE!=1 and zone_demand_popularity=POPULARITY_INDEX_5==1 and pickUpHourOfDay=LATENIGHT!=1 and city=Pune==1 and booking_type=outstation!=1 and pickUpHourOfDay=MORNING!=1",
                "class_counts": [
                  123.0,
                  78.0
                ],
                "impurity": 0.4749,
                "is_leaf": true,
                "type": "leaf",
                "prediction": 0,
                "probabilities": [
                  0.6119,
                  0.3881
                ]
              },
              "right": {
                "depth": 6,
                "n_samples": 90.0,
                "ancestry": "pickUpHourOfDay=VERYLATE!=1 and zone_demand_popularity=POPULARITY_INDEX_5==1 and pickUpHourOfDay=LATENIGHT!=1 and city=Pune==1 and booking_type=outstation!=1 and pickUpHourOfDay=MORNING==1",
                "class_counts": [
                  73.0,
                  17.0
                ],
                "impurity": 0.3064,
                "is_leaf": true,
                "type": "leaf",
                "prediction": 0,
                "probabilities": [
                  0.8111,
                  0.1889
                ]
              }
            },
            "right": {
              "depth": 5,
              "n_samples": 62.0,
              "ancestry": "pickUpHourOfDay=VERYLATE!=1 and zone_demand_popularity=POPULARITY_INDEX_5==1 and pickUpHourOfDay=LATENIGHT!=1 and city=Pune==1 and booking_type=outstation==1",
              "class_counts": [
                56.0,
                6.0
              ],
              "impurity": 0.1748,
              "is_leaf": true,
              "type": "leaf",
              "prediction": 0,
              "probabilities": [
                0.9032,
                0.0968
              ]
            }
          }
        },
        "right": {
          "depth": 3,
          "n_samples": 139.0,
          "ancestry": "pickUpHourOfDay=VERYLATE!=1 and zone_demand_popularity=POPULARITY_INDEX_5==1 and pickUpHourOfDay=LATENIGHT==1",
          "class_counts": [
            81.0,
            58.0
          ],
          "impurity": 0.4863,
          "is_leaf": false,
          "type": "split",
          "feature_name": "city=Mumbai",
          "feature_idx": 14,
          "split_condition": "city=Mumbai == 1",
          "left_condition": "city=Mumbai == 0 (FALSE/NOT)",
          "right_condition": "city=Mumbai == 1 (TRUE)",
          "left": {
            "depth": 4,
            "n_samples": 85.0,
            "ancestry": "pickUpHourOfDay=VERYLATE!=1 and zone_demand_popularity=POPULARITY_INDEX_5==1 and pickUpHourOfDay=LATENIGHT==1 and city=Mumbai!=1",
            "class_counts": [
              43.0,
              42.0
            ],
            "impurity": 0.4999,
            "is_leaf": true,
            "type": "leaf",
            "prediction": 0,
            "probabilities": [
              0.5059,
              0.4941
            ]
          },
          "right": {
            "depth": 4,
            "n_samples": 54.0,
            "ancestry": "pickUpHourOfDay=VERYLATE!=1 and zone_demand_popularity=POPULARITY_INDEX_5==1 and pickUpHourOfDay=LATENIGHT==1 and city=Mumbai==1",
            "class_counts": [
              38.0,
              16.0
            ],
            "impurity": 0.417,
            "is_leaf": true,
            "type": "leaf",
            "prediction": 0,
            "probabilities": [
              0.7037,
              0.2963
            ]
          }
        }
      }
    },
    "right": {
      "depth": 1,
      "n_samples": 2330.0,
      "ancestry": "pickUpHourOfDay=VERYLATE==1",
      "class_counts": [
        1808.0,
        522.0
      ],
      "impurity": 0.3477,
      "is_leaf": false,
      "type": "split",
      "feature_name": "city=Delhi NCR",
      "feature_idx": 12,
      "split_condition": "city=Delhi NCR == 1",
      "left_condition": "city=Delhi NCR == 0 (FALSE/NOT)",
      "right_condition": "city=Delhi NCR == 1 (TRUE)",
      "left": {
        "depth": 2,
        "n_samples": 2162.0,
        "ancestry": "pickUpHourOfDay=VERYLATE==1 and city=Delhi NCR!=1",
        "class_counts": [
          1731.0,
          431.0
        ],
        "impurity": 0.3192,
        "is_leaf": false,
        "type": "split",
        "feature_name": "dayType=WEEKEND",
        "feature_idx": 18,
        "split_condition": "dayType=WEEKEND == 1",
        "left_condition": "dayType=WEEKEND == 0 (FALSE/NOT)",
        "right_condition": "dayType=WEEKEND == 1 (TRUE)",
        "left": {
          "depth": 3,
          "n_samples": 868.0,
          "ancestry": "pickUpHourOfDay=VERYLATE==1 and city=Delhi NCR!=1 and dayType=WEEKEND!=1",
          "class_counts": [
            767.0,
            101.0
          ],
          "impurity": 0.2056,
          "is_leaf": false,
          "type": "split",
          "feature_name": "zone_demand_popularity=POPULARITY_INDEX_5",
          "feature_idx": 353,
          "split_condition": "zone_demand_popularity=POPULARITY_INDEX_5 == 1",
          "left_condition": "zone_demand_popularity=POPULARITY_INDEX_5 == 0 (FALSE/NOT)",
          "right_condition": "zone_demand_popularity=POPULARITY_INDEX_5 == 1 (TRUE)",
          "left": {
            "depth": 4,
            "n_samples": 811.0,
            "ancestry": "pickUpHourOfDay=VERYLATE==1 and city=Delhi NCR!=1 and dayType=WEEKEND!=1 and zone_demand_popularity=POPULARITY_INDEX_5!=1",
            "class_counts": [
              728.0,
              83.0
            ],
            "impurity": 0.1837,
            "is_leaf": false,
            "type": "split",
            "feature_name": "city=Hyderabad",
            "feature_idx": 13,
            "split_condition": "city=Hyderabad == 1",
            "left_condition": "city=Hyderabad == 0 (FALSE/NOT)",
            "right_condition": "city=Hyderabad == 1 (TRUE)",
            "left": {
              "depth": 5,
              "n_samples": 721.0,
              "ancestry": "pickUpHourOfDay=VERYLATE==1 and city=Delhi NCR!=1 and dayType=WEEKEND!=1 and zone_demand_popularity=POPULARITY_INDEX_5!=1 and city=Hyderabad!=1",
              "class_counts": [
                661.0,
                60.0
              ],
              "impurity": 0.1526,
              "is_leaf": false,
              "type": "split",
              "feature_name": "zone_demand_popularity=POPULARITY_INDEX_1",
              "feature_idx": 349,
              "split_condition": "zone_demand_popularity=POPULARITY_INDEX_1 == 1",
              "left_condition": "zone_demand_popularity=POPULARITY_INDEX_1 == 0 (FALSE/NOT)",
              "right_condition": "zone_demand_popularity=POPULARITY_INDEX_1 == 1 (TRUE)",
              "left": {
                "depth": 6,
                "n_samples": 395.0,
                "ancestry": "pickUpHourOfDay=VERYLATE==1 and city=Delhi NCR!=1 and dayType=WEEKEND!=1 and zone_demand_popularity=POPULARITY_INDEX_5!=1 and city=Hyderabad!=1 and zone_demand_popularity=POPULARITY_INDEX_1!=1",
                "class_counts": [
                  350.0,
                  45.0
                ],
                "impurity": 0.2019,
                "is_leaf": true,
                "type": "leaf",
                "prediction": 0,
                "probabilities": [
                  0.8861,
                  0.1139
                ]
              },
              "right": {
                "depth": 6,
                "n_samples": 326.0,
                "ancestry": "pickUpHourOfDay=VERYLATE==1 and city=Delhi NCR!=1 and dayType=WEEKEND!=1 and zone_demand_popularity=POPULARITY_INDEX_5!=1 and city=Hyderabad!=1 and zone_demand_popularity=POPULARITY_INDEX_1==1",
                "class_counts": [
                  311.0,
                  15.0
                ],
                "impurity": 0.0878,
                "is_leaf": true,
                "type": "leaf",
                "prediction": 0,
                "probabilities": [
                  0.954,
                  0.046
                ]
              }
            },
            "right": {
              "depth": 5,
              "n_samples": 90.0,
              "ancestry": "pickUpHourOfDay=VERYLATE==1 and city=Delhi NCR!=1 and dayType=WEEKEND!=1 and zone_demand_popularity=POPULARITY_INDEX_5!=1 and city=Hyderabad==1",
              "class_counts": [
                67.0,
                23.0
              ],
              "impurity": 0.3805,
              "is_leaf": true,
              "type": "leaf",
              "prediction": 0,
              "probabilities": [
                0.7444,
                0.2556
              ]
            }
          },
          "right": {
            "depth": 4,
            "n_samples": 57.0,
            "ancestry": "pickUpHourOfDay=VERYLATE==1 and city=Delhi NCR!=1 and dayType=WEEKEND!=1 and zone_demand_popularity=POPULARITY_INDEX_5==1",
            "class_counts": [
              39.0,
              18.0
            ],
            "impurity": 0.4321,
            "is_leaf": true,
            "type": "leaf",
            "prediction": 0,
            "probabilities": [
              0.6842,
              0.3158
            ]
          }
        },
        "right": {
          "depth": 3,
          "n_samples": 1294.0,
          "ancestry": "pickUpHourOfDay=VERYLATE==1 and city=Delhi NCR!=1 and dayType=WEEKEND==1",
          "class_counts": [
            964.0,
            330.0
          ],
          "impurity": 0.38,
          "is_leaf": false,
          "type": "split",
          "feature_name": "city=Chennai",
          "feature_idx": 11,
          "split_condition": "city=Chennai == 1",
          "left_condition": "city=Chennai == 0 (FALSE/NOT)",
          "right_condition": "city=Chennai == 1 (TRUE)",
          "left": {
            "depth": 4,
            "n_samples": 1228.0,
            "ancestry": "pickUpHourOfDay=VERYLATE==1 and city=Delhi NCR!=1 and dayType=WEEKEND==1 and city=Chennai!=1",
            "class_counts": [
              901.0,
              327.0
            ],
            "impurity": 0.3908,
            "is_leaf": false,
            "type": "split",
            "feature_name": "zone_demand_popularity=POPULARITY_INDEX_4",
            "feature_idx": 352,
            "split_condition": "zone_demand_popularity=POPULARITY_INDEX_4 == 1",
            "left_condition": "zone_demand_popularity=POPULARITY_INDEX_4 == 0 (FALSE/NOT)",
            "right_condition": "zone_demand_popularity=POPULARITY_INDEX_4 == 1 (TRUE)",
            "left": {
              "depth": 5,
              "n_samples": 1079.0,
              "ancestry": "pickUpHourOfDay=VERYLATE==1 and city=Delhi NCR!=1 and dayType=WEEKEND==1 and city=Chennai!=1 and zone_demand_popularity=POPULARITY_INDEX_4!=1",
              "class_counts": [
                818.0,
                261.0
              ],
              "impurity": 0.3668,
              "is_leaf": false,
              "type": "split",
              "feature_name": "zone=216",
              "feature_idx": 87,
              "split_condition": "zone=216 == 1",
              "left_condition": "zone=216 == 0 (FALSE/NOT)",
              "right_condition": "zone=216 == 1 (TRUE)",
              "left": {
                "depth": 6,
                "n_samples": 996.0,
                "ancestry": "pickUpHourOfDay=VERYLATE==1 and city=Delhi NCR!=1 and dayType=WEEKEND==1 and city=Chennai!=1 and zone_demand_popularity=POPULARITY_INDEX_4!=1 and zone=216!=1",
                "class_counts": [
                  741.0,
                  255.0
                ],
                "impurity": 0.381,
                "is_leaf": true,
                "type": "leaf",
                "prediction": 0,
                "probabilities": [
                  0.744,
                  0.256
                ]
              },
              "right": {
                "depth": 6,
                "n_samples": 83.0,
                "ancestry": "pickUpHourOfDay=VERYLATE==1 and city=Delhi NCR!=1 and dayType=WEEKEND==1 and city=Chennai!=1 and zone_demand_popularity=POPULARITY_INDEX_4!=1 and zone=216==1",
                "class_counts": [
                  77.0,
                  6.0
                ],
                "impurity": 0.1341,
                "is_leaf": true,
                "type": "leaf",
                "prediction": 0,
                "probabilities": [
                  0.9277,
                  0.0723
                ]
              }
            },
            "right": {
              "depth": 5,
              "n_samples": 149.0,
              "ancestry": "pickUpHourOfDay=VERYLATE==1 and city=Delhi NCR!=1 and dayType=WEEKEND==1 and city=Chennai!=1 and zone_demand_popularity=POPULARITY_INDEX_4==1",
              "class_counts": [
                83.0,
                66.0
              ],
              "impurity": 0.4935,
              "is_leaf": false,
              "type": "split",
              "feature_name": "city=Mumbai",
              "feature_idx": 14,
              "split_condition": "city=Mumbai == 1",
              "left_condition": "city=Mumbai == 0 (FALSE/NOT)",
              "right_condition": "city=Mumbai == 1 (TRUE)",
              "left": {
                "depth": 6,
                "n_samples": 66.0,
                "ancestry": "pickUpHourOfDay=VERYLATE==1 and city=Delhi NCR!=1 and dayType=WEEKEND==1 and city=Chennai!=1 and zone_demand_popularity=POPULARITY_INDEX_4==1 and city=Mumbai!=1",
                "class_counts": [
                  40.0,
                  26.0
                ],
                "impurity": 0.4775,
                "is_leaf": true,
                "type": "leaf",
                "prediction": 0,
                "probabilities": [
                  0.6061,
                  0.3939
                ]
              },
              "right": {
                "depth": 6,
                "n_samples": 83.0,
                "ancestry": "pickUpHourOfDay=VERYLATE==1 and city=Delhi NCR!=1 and dayType=WEEKEND==1 and city=Chennai!=1 and zone_demand_popularity=POPULARITY_INDEX_4==1 and city=Mumbai==1",
                "class_counts": [
                  43.0,
                  40.0
                ],
                "impurity": 0.4993,
                "is_leaf": true,
                "type": "leaf",
                "prediction": 0,
                "probabilities": [
                  0.5181,
                  0.4819
                ]
              }
            }
          },
          "right": {
            "depth": 4,
            "n_samples": 66.0,
            "ancestry": "pickUpHourOfDay=VERYLATE==1 and city=Delhi NCR!=1 and dayType=WEEKEND==1 and city=Chennai==1",
            "class_counts": [
              63.0,
              3.0
            ],
            "impurity": 0.0868,
            "is_leaf": true,
            "type": "leaf",
            "prediction": 0,
            "probabilities": [
              0.9545,
              0.0455
            ]
          }
        }
      },
      "right": {
        "depth": 2,
        "n_samples": 168.0,
        "ancestry": "pickUpHourOfDay=VERYLATE==1 and city=Delhi NCR==1",
        "class_counts": [
          77.0,
          91.0
        ],
        "impurity": 0.4965,
        "is_leaf": false,
        "type": "split",
        "feature_name": "zone_demand_popularity=POPULARITY_INDEX_2",
        "feature_idx": 350,
        "split_condition": "zone_demand_popularity=POPULARITY_INDEX_2 == 1",
        "left_condition": "zone_demand_popularity=POPULARITY_INDEX_2 == 0 (FALSE/NOT)",
        "right_condition": "zone_demand_popularity=POPULARITY_INDEX_2 == 1 (TRUE)",
        "left": {
          "depth": 3,
          "n_samples": 111.0,
          "ancestry": "pickUpHourOfDay=VERYLATE==1 and city=Delhi NCR==1 and zone_demand_popularity=POPULARITY_INDEX_2!=1",
          "class_counts": [
            47.0,
            64.0
          ],
          "impurity": 0.4883,
          "is_leaf": false,
          "type": "split",
          "feature_name": "zone_demand_popularity=POPULARITY_INDEX_4",
          "feature_idx": 352,
          "split_condition": "zone_demand_popularity=POPULARITY_INDEX_4 == 1",
          "left_condition": "zone_demand_popularity=POPULARITY_INDEX_4 == 0 (FALSE/NOT)",
          "right_condition": "zone_demand_popularity=POPULARITY_INDEX_4 == 1 (TRUE)",
          "left": {
            "depth": 4,
            "n_samples": 60.0,
            "ancestry": "pickUpHourOfDay=VERYLATE==1 and city=Delhi NCR==1 and zone_demand_popularity=POPULARITY_INDEX_2!=1 and zone_demand_popularity=POPULARITY_INDEX_4!=1",
            "class_counts": [
              22.0,
              38.0
            ],
            "impurity": 0.4644,
            "is_leaf": true,
            "type": "leaf",
            "prediction": 1,
            "probabilities": [
              0.3667,
              0.6333
            ]
          },
          "right": {
            "depth": 4,
            "n_samples": 51.0,
            "ancestry": "pickUpHourOfDay=VERYLATE==1 and city=Delhi NCR==1 and zone_demand_popularity=POPULARITY_INDEX_2!=1 and zone_demand_popularity=POPULARITY_INDEX_4==1",
            "class_counts": [
              25.0,
              26.0
            ],
            "impurity": 0.4998,
            "is_leaf": true,
            "type": "leaf",
            "prediction": 1,
            "probabilities": [
              0.4902,
              0.5098
            ]
          }
        },
        "right": {
          "depth": 3,
          "n_samples": 57.0,
          "ancestry": "pickUpHourOfDay=VERYLATE==1 and city=Delhi NCR==1 and zone_demand_popularity=POPULARITY_INDEX_2==1",
          "class_counts": [
            30.0,
            27.0
          ],
          "impurity": 0.4986,
          "is_leaf": true,
          "type": "leaf",
          "prediction": 0,
          "probabilities": [
            0.5263,
            0.4737
          ]
        }
      }
    }
  }
}