{
  "booking_type=12hr": 0,
  "booking_type=2hr": 1,
  "booking_type=4hr": 2,
  "booking_type=5hr": 3,
  "booking_type=6hr": 4,
  "booking_type=8hr": 5,
  "booking_type=one_way_outstation": 6,
  "booking_type=one_way_trip": 7,
  "booking_type=outstation": 8,
  "booking_type=round_trip": 9,
  "city=Bangalore": 10,
  "city=Chennai": 11,
  "city=Delhi NCR": 12,
  "city=Hyderabad": 13,
  "city=Mumbai": 14,
  "city=Pune": 15,
  "dayType=FRIDAY": 16,
  "dayType=NORMAL_WEEKDAY": 17,
  "dayType=WEEKEND": 18,
  "estimated_usage_bins=GT_1_LTE_2_HOURS": 19,
  "estimated_usage_bins=GT_2_LTE_3_HOURS": 20,
  "estimated_usage_bins=GT_3_LTE_4_HOURS": 21,
  "estimated_usage_bins=GT_4_LTE_6_HOURS": 22,
  "estimated_usage_bins=GT_6_LTE_8_HOURS": 23,
  "estimated_usage_bins=GT_8_HOURS": 24,
  "estimated_usage_bins=LTE_1_HOUR": 25,
  "estimated_usage_bins=NOT_SPECIFIED": 26,
  "pickUpHourOfDay=AFTERNOON": 27,
  "pickUpHourOfDay=EARLY": 28,
  "pickUpHourOfDay=EVENING": 29,
  "pickUpHourOfDay=LATENIGHT": 30,
  "pickUpHourOfDay=MORNING": 31,
  "pickUpHourOfDay=NIGHT": 32,
  "pickUpHourOfDay=VERYLATE": 33,
  "sla=Immediate": 34,
  "sla=Scheduled": 35,
  "source=B2B Portal": 36,
  "source=Phone": 37,
  "source=android": 38,
  "source=ios": 39,
  "source=msite": 40,
  "source=website": 41,
  "zone=100": 42,
  "zone=101": 43,
  "zone=102": 44,
  "zone=103": 45,
  "zone=105": 46,
  "zone=106": 47,
  "zone=107": 48,
  "zone=111": 49,
  "zone=141": 50,
  "zone=142": 51,
  "zone=143": 52,
  "zone=144": 53,
  "zone=150": 54,
  "zone=151": 55,
  "zone=152": 56,
  "zone=153": 57,
  "zone=154": 58,
  "zone=155": 59,
  "zone=156": 60,
  "zone=157": 61,
  "zone=158": 62,
  "zone=159": 63,
  "zone=160": 64,
  "zone=161": 65,
  "zone=162": 66,
  "zone=163": 67,
  "zone=164": 68,
  "zone=166": 69,
  "zone=167": 70,
  "zone=171": 71,
  "zone=173": 72,
  "zone=174": 73,
  "zone=175": 74,
  "zone=190": 75,
  "zone=191": 76,
  "zone=193": 77,
  "zone=194": 78,
  "zone=200": 79,
  "zone=202": 80,
  "zone=203": 81,
  "zone=205": 82,
  "zone=206": 83,
  "zone=207": 84,
  "zone=208": 85,
  "zone=209": 86,
  "zone=216": 87,
  "zone=217": 88,
  "zone=218": 89,
  "zone=219": 90,
  "zone=220": 91,
  "zone=221": 92,
  "zone=223": 93,
  "zone=227": 94,
  "zone=230": 95,
  "zone=231": 96,
  "zone=236": 97,
  "zone=239": 98,
  "zone=241": 99,
  "zone=242": 100,
  "zone=243": 101,
  "zone=244": 102,
  "zone=245": 103,
  "zone=246": 104,
  "zone=248": 105,
  "zone=249": 106,
  "zone=250": 107,
  "zone=251": 108,
  "zone=252": 109,
  "zone=253": 110,
  "zone=254": 111,
  "zone=256": 112,
  "zone=257": 113,
  "zone=258": 114,
  "zone=260": 115,
  "zone=261": 116,
  "zone=262": 117,
  "zone=263": 118,
  "zone=264": 119,
  "zone=267": 120,
  "zone=268": 121,
  "zone=269": 122,
  "zone=270": 123,
  "zone=275": 124,
  "zone=276": 125,
  "zone=277": 126,
  "zone=278": 127,
  "zone=281": 128,
  "zone=282": 129,
  "zone=283": 130,
  "zone=289": 131,
  "zone=296": 132,
  "zone=297": 133,
  "zone=298": 134,
  "zone=299": 135,
  "zone=300": 136,
  "zone=301": 137,
  "zone=304": 138,
  "zone=305": 139,
  "zone=306": 140,
  "zone=307": 141,
  "zone=308": 142,
  "zone=310": 143,
  "zone=311": 144,
  "zone=313": 145,
  "zone=314": 146,
  "zone=315": 147,
  "zone=316": 148,
  "zone=317": 149,
  "zone=318": 150,
  "zone=319": 151,
  "zone=320": 152,
  "zone=322": 153,
  "zone=324": 154,
  "zone=325": 155,
  "zone=326": 156,
  "zone=327": 157,
  "zone=328": 158,
  "zone=329": 159,
  "zone=330": 160,
  "zone=331": 161,
  "zone=332": 162,
  "zone=333": 163,
  "zone=334": 164,
  "zone=335": 165,
  "zone=337": 166,
  "zone=338": 167,
  "zone=339": 168,
  "zone=340": 169,
  "zone=341": 170,
  "zone=342": 171,
  "zone=344": 172,
  "zone=345": 173,
  "zone=346": 174,
  "zone=347": 175,
  "zone=348": 176,
  "zone=349": 177,
  "zone=350": 178,
  "zone=351": 179,
  "zone=352": 180,
  "zone=353": 181,
  "zone=354": 182,
  "zone=355": 183,
  "zone=356": 184,
  "zone=357": 185,
  "zone=359": 186,
  "zone=360": 187,
  "zone=361": 188,
  "zone=363": 189,
  "zone=364": 190,
  "zone=365": 191,
  "zone=367": 192,
  "zone=368": 193,
  "zone=370": 194,
  "zone=372": 195,
  "zone=374": 196,
  "zone=375": 197,
  "zone=376": 198,
  "zone=377": 199,
  "zone=378": 200,
  "zone=379": 201,
  "zone=380": 202,
  "zone=381": 203,
  "zone=382": 204,
  "zone=383": 205,
  "zone=384": 206,
  "zone=385": 207,
  "zone=386": 208,
  "zone=387": 209,
  "zone=388": 210,
  "zone=389": 211,
  "zone=390": 212,
  "zone=391": 213,
  "zone=392": 214,
  "zone=393": 215,
  "zone=395": 216,
  "zone=396": 217,
  "zone=397": 218,
  "zone=398": 219,
  "zone=399": 220,
  "zone=400": 221,
  "zone=401": 222,
  "zone=403": 223,
  "zone=404": 224,
  "zone=405": 225,
  "zone=406": 226,
  "zone=408": 227,
  "zone=409": 228,
  "zone=410": 229,
  "zone=411": 230,
  "zone=412": 231,
  "zone=413": 232,
  "zone=414": 233,
  "zone=415": 234,
  "zone=416": 235,
  "zone=417": 236,
  "zone=418": 237,
  "zone=419": 238,
  "zone=420": 239,
  "zone=421": 240,
  "zone=422": 241,
  "zone=423": 242,
  "zone=424": 243,
  "zone=425": 244,
  "zone=426": 245,
  "zone=427": 246,
  "zone=428": 247,
  "zone=429": 248,
  "zone=430": 249,
  "zone=431": 250,
  "zone=432": 251,
  "zone=433": 252,
  "zone=434": 253,
  "zone=435": 254,
  "zone=436": 255,
  "zone=437": 256,
  "zone=438": 257,
  "zone=439": 258,
  "zone=441": 259,
  "zone=442": 260,
  "zone=443": 261,
  "zone=444": 262,
  "zone=445": 263,
  "zone=446": 264,
  "zone=447": 265,
  "zone=448": 266,
  "zone=449": 267,
  "zone=450": 268,
  "zone=451": 269,
  "zone=452": 270,
  "zone=453": 271,
  "zone=454": 272,
  "zone=455": 273,
  "zone=456": 274,
  "zone=457": 275,
  "zone=458": 276,
  "zone=459": 277,
  "zone=460": 278,
  "zone=461": 279,
  "zone=462": 280,
  "zone=465": 281,
  "zone=466": 282,
  "zone=467": 283,
  "zone=468": 284,
  "zone=469": 285,
  "zone=472": 286,
  "zone=475": 287,
  "zone=476": 288,
  "zone=477": 289,
  "zone=478": 290,
  "zone=479": 291,
  "zone=48": 292,
  "zone=480": 293,
  "zone=481": 294,
  "zone=482": 295,
  "zone=484": 296,
  "zone=485": 297,
  "zone=486": 298,
  "zone=488": 299,
  "zone=489": 300,
  "zone=49": 301,
  "zone=490": 302,
  "zone=491": 303,
  "zone=492": 304,
  "zone=493": 305,
  "zone=494": 306,
  "zone=495": 307,
  "zone=496": 308,
  "zone=497": 309,
  "zone=498": 310,
  "zone=499": 311,
  "zone=50": 312,
  "zone=500": 313,
  "zone=501": 314,
  "zone=502": 315,
  "zone=503": 316,
  "zone=504": 317,
  "zone=505": 318,
  "zone=506": 319,
  "zone=507": 320,
  "zone=508": 321,
  "zone=509": 322,
  "zone=510": 323,
  "zone=511": 324,
  "zone=52": 325,
  "zone=53": 326,
  "zone=54": 327,
  "zone=55": 328,
  "zone=56": 329,
  "zone=57": 330,
  "zone=58": 331,
  "zone=60": 332,
  "zone=62": 333,
  "zone=67": 334,
  "zone=71": 335,
  "zone=74": 336,
  "zone=75": 337,
  "zone=77": 338,
  "zone=81": 339,
  "zone=82": 340,
  "zone=84": 341,
  "zone=86": 342,
  "zone=89": 343,
  "zone=90": 344,
  "zone=92": 345,
  "zone=96": 346,
  "zone=97": 347,
  "zone=99": 348,
  "zone_demand_popularity=POPULARITY_INDEX_1": 349,
  "zone_demand_popularity=POPULARITY_INDEX_2": 350,
  "zone_demand_popularity=POPULARITY_INDEX_3": 351,
  "zone_demand_popularity=POPULARITY_INDEX_4": 352,
  "zone_demand_popularity=POPULARITY_INDEX_5": 353
}